{"50002":{"n":"Agneaux","p":11188,"e":-1.1,"v":19,"d":"","po":4266},"50003":{"n":"Agon-Coutainville","p":9848,"e":5.8,"v":9,"d":"","po":3013},"50004":{"n":"Airel","p":10643,"e":1.4,"v":16,"d":"","po":527},"50006":{"n":"Amigny","p":12915,"e":6.9,"v":9,"d":"","po":153},"50008":{"n":"Anctoville-sur-Boscq","p":11375,"e":1.4,"v":9,"d":"","po":438},"50013":{"n":"Anneville-en-Saire","p":10421,"e":5.8,"v":8,"d":"","po":376},"50016":{"n":"Appeville","p":11786,"e":3.6,"v":8,"d":"","po":193},"50019":{"n":"Aucey-la-Plaine","p":9755,"e":3.2,"v":20,"d":"","po":413},"50021":{"n":"Audouville-la-Hubert","p":11812,"e":7.3,"v":10,"d":"","po":76},"50022":{"n":"Aumeville-Lestre","p":11126,"e":3.8,"v":8,"d":"","po":125},"50023":{"n":"Auvers","p":10249,"e":6.1,"v":19,"d":"","po":689},"50024":{"n":"Auxais","p":9592,"e":7.7,"v":20,"d":"","po":173},"50025":{"n":"Avranches","p":10513,"e":2.8,"v":119,"d":"","po":10225},"50026":{"n":"Azeville","p":10639,"e":5.9,"v":6,"d":"","po":77},"50027":{"n":"Bacilly","p":12405,"e":-0.7,"v":14,"d":"","po":935},"50028":{"n":"La Baleine","p":10923,"e":0.4,"v":6,"d":"","po":106},"50029":{"n":"Barenton","p":10593,"e":4.0,"v":20,"d":"","po":1166},"50030":{"n":"Barfleur","p":10225,"e":6.4,"v":7,"d":"","po":545},"50031":{"n":"Barneville-Carteret","p":10345,"e":1.4,"v":9,"d":"","po":2181},"50032":{"n":"La Barre-de-Semilly","p":9275,"e":5.7,"v":5,"d":"","po":1033},"50033":{"n":"Baubigny","p":9972,"e":-1.4,"v":17,"d":"","po":134},"50034":{"n":"Baudre","p":9247,"e":7.4,"v":9,"d":"","po":595},"50036":{"n":"Baupte","p":9846,"e":5.8,"v":18,"d":"","po":428},"50038":{"n":"Beauchamps","p":11078,"e":6.5,"v":9,"d":"","po":438},"50039":{"n":"Beaucoudray","p":12631,"e":1.8,"v":19,"d":"","po":136},"50040":{"n":"Beauficel","p":11144,"e":0.5,"v":15,"d":"","po":119},"50041":{"n":"La Hague","p":12730,"e":7.9,"v":171,"d":"","po":11444},"50042":{"n":"Beauvoir","p":10067,"e":4.9,"v":5,"d":"","po":435},"50044":{"n":"Belval","p":13144,"e":6.3,"v":11,"d":"","po":334},"50045":{"n":"Benoîtville","p":10500,"e":-0.1,"v":5,"d":"","po":612},"50046":{"n":"Bérigny","p":10061,"e":4.9,"v":5,"d":"","po":442},"50048":{"n":"Beslon","p":10417,"e":4.6,"v":8,"d":"","po":550},"50049":{"n":"Besneville","p":11971,"e":3.3,"v":18,"d":"","po":662},"50050":{"n":"Beuvrigny","p":11913,"e":2.5,"v":14,"d":"","po":130},"50052":{"n":"Beuzeville-la-Bastille","p":11015,"e":-1.3,"v":10,"d":"","po":147},"50054":{"n":"Biéville","p":10734,"e":-1.1,"v":20,"d":"","po":196},"50055":{"n":"Biniville","p":10748,"e":-1.6,"v":10,"d":"","po":116},"50058":{"n":"Blainville-sur-Mer","p":11504,"e":3.5,"v":5,"d":"","po":1604},"50059":{"n":"Blosville","p":8943,"e":7.6,"v":7,"d":"","po":322},"50060":{"n":"La Bloutière","p":10653,"e":5.3,"v":18,"d":"","po":430},"50062":{"n":"Boisyvon","p":11740,"e":-1.8,"v":8,"d":"","po":100},"50064":{"n":"La Bonneville","p":11618,"e":6.5,"v":14,"d":"","po":176},"50066":{"n":"Jullouville","p":10025,"e":4.5,"v":12,"d":"","po":2401},"50069":{"n":"Bourguenolles","p":11223,"e":3.3,"v":17,"d":"","po":343},"50070":{"n":"Boutteville","p":12548,"e":-1.0,"v":17,"d":"","po":59},"50072":{"n":"Brainville","p":10136,"e":-1.3,"v":10,"d":"","po":213},"50074":{"n":"Brécey","p":9496,"e":3.1,"v":15,"d":"","po":2166},"50076":{"n":"Bréhal","p":10289,"e":6.9,"v":8,"d":"","po":3480},"50077":{"n":"Bretteville","p":12175,"e":2.2,"v":5,"d":"","po":1006},"50078":{"n":"Bretteville-sur-Ay","p":11272,"e":3.5,"v":5,"d":"","po":436},"50079":{"n":"Breuville","p":11802,"e":4.0,"v":7,"d":"","po":405},"50081":{"n":"Bréville-sur-Mer","p":10898,"e":0.4,"v":19,"d":"","po":785},"50082":{"n":"Bricquebec-en-Cotentin","p":12669,"e":6.9,"v":50,"d":"","po":5888},"50083":{"n":"Bricquebosq","p":10585,"e":2.1,"v":16,"d":"","po":638},"50084":{"n":"Bricqueville-la-Blouette","p":11974,"e":3.1,"v":11,"d":"","po":533},"50085":{"n":"Bricqueville-sur-Mer","p":12530,"e":2.5,"v":19,"d":"","po":1263},"50086":{"n":"Brillevast","p":10155,"e":1.6,"v":12,"d":"","po":321},"50087":{"n":"Brix","p":10993,"e":-0.7,"v":16,"d":"","po":2146},"50088":{"n":"Brouains","p":13382,"e":-1.2,"v":14,"d":"","po":140},"50090":{"n":"Buais-Les-Monts","p":9962,"e":7.6,"v":8,"d":"","po":612},"50092":{"n":"Cambernon","p":10954,"e":5.1,"v":7,"d":"","po":693},"50093":{"n":"Cametours","p":12123,"e":3.3,"v":12,"d":"","po":435},"50094":{"n":"Camprond","p":11642,"e":6.3,"v":18,"d":"","po":386},"50095":{"n":"Canisy","p":11259,"e":-0.9,"v":11,"d":"","po":1723},"50096":{"n":"Canteloup","p":9379,"e":5.0,"v":7,"d":"","po":216},"50097":{"n":"Canville-la-Rocque","p":9762,"e":0.3,"v":19,"d":"","po":119},"50098":{"n":"Carantilly","p":12394,"e":2.3,"v":17,"d":"","po":619},"50099":{"n":"Carentan-les-Marais","p":10710,"e":-0.2,"v":152,"d":"","po":10220},"50101":{"n":"Carneville","p":11063,"e":3.1,"v":6,"d":"","po":240},"50102":{"n":"Carolles","p":10027,"e":-0.3,"v":10,"d":"","po":768},"50105":{"n":"Catteville","p":10161,"e":7.6,"v":7,"d":"","po":103},"50106":{"n":"Cavigny","p":9391,"e":3.4,"v":19,"d":"","po":268},"50108":{"n":"Céaux","p":10104,"e":7.6,"v":6,"d":"","po":413},"50109":{"n":"Cérences","p":10534,"e":3.9,"v":18,"d":"","po":1806},"50110":{"n":"Cerisy-la-Forêt","p":12445,"e":1.9,"v":7,"d":"","po":1014},"50111":{"n":"Cerisy-la-Salle","p":12959,"e":2.3,"v":5,"d":"","po":1026},"50112":{"n":"La Chaise-Baudouin","p":11918,"e":6.8,"v":19,"d":"","po":443},"50115":{"n":"Le Grippon","p":10457,"e":7.1,"v":19,"d":"","po":390},"50117":{"n":"Champeaux","p":10164,"e":2.6,"v":7,"d":"","po":341},"50118":{"n":"Champrepus","p":10945,"e":-1.0,"v":10,"d":"","po":322},"50120":{"n":"Chanteloup","p":11272,"e":-0.5,"v":10,"d":"","po":393},"50121":{"n":"La Chapelle-Cécelin","p":12393,"e":1.1,"v":6,"d":"","po":244},"50124":{"n":"La Chapelle-Urée","p":11511,"e":-1.2,"v":15,"d":"","po":171},"50126":{"n":"Chavoy","p":9929,"e":5.5,"v":9,"d":"","po":130},"50129":{"n":"Cherbourg-en-Cotentin","p":11191,"e":1.6,"v":246,"d":"","po":78028},"50130":{"n":"Chérencé-le-Héron","p":10921,"e":3.6,"v":19,"d":"","po":438},"50135":{"n":"Clitourps","p":9373,"e":0.2,"v":15,"d":"","po":228},"50137":{"n":"La Colombe","p":13018,"e":-1.6,"v":6,"d":"","po":627},"50138":{"n":"Colomby","p":10295,"e":5.6,"v":14,"d":"","po":566},"50139":{"n":"Condé-sur-Vire","p":12262,"e":-1.5,"v":9,"d":"","po":4136},"50142":{"n":"Vicq-sur-Mer","p":11951,"e":2.0,"v":17,"d":"","po":1083},"50143":{"n":"Coudeville-sur-Mer","p":11613,"e":-0.6,"v":10,"d":"","po":873},"50144":{"n":"Coulouvray-Boisbenâtre","p":10895,"e":7.6,"v":8,"d":"","po":529},"50145":{"n":"Courcy","p":11658,"e":2.5,"v":15,"d":"","po":623},"50146":{"n":"Courtils","p":10890,"e":5.2,"v":5,"d":"","po":219},"50147":{"n":"Coutances","p":11631,"e":1.2,"v":47,"d":"","po":8372},"50148":{"n":"Couvains","p":10822,"e":-1.8,"v":15,"d":"","po":577},"50149":{"n":"Couville","p":11573,"e":5.7,"v":18,"d":"","po":1228},"50150":{"n":"Crasville","p":10298,"e":7.1,"v":12,"d":"","po":223},"50151":{"n":"Créances","p":10355,"e":-0.3,"v":12,"d":"","po":2079},"50152":{"n":"Les Cresnays","p":13174,"e":1.8,"v":20,"d":"","po":230},"50155":{"n":"Crollon","p":11444,"e":-0.2,"v":12,"d":"","po":298},"50156":{"n":"Crosville-sur-Douve","p":9971,"e":-1.6,"v":19,"d":"","po":62},"50158":{"n":"Cuves","p":10504,"e":-0.8,"v":14,"d":"","po":263},"50159":{"n":"Dangy","p":9657,"e":6.5,"v":9,"d":"","po":660},"50161":{"n":"Le Dézert","p":12131,"e":0.7,"v":13,"d":"","po":605},"50162":{"n":"Digosville","p":12829,"e":4.6,"v":17,"d":"","po":1665},"50164":{"n":"Domjean","p":10021,"e":6.7,"v":12,"d":"","po":998},"50165":{"n":"Donville-les-Bains","p":10358,"e":6.1,"v":6,"d":"","po":3133},"50166":{"n":"Doville","p":12089,"e":-0.4,"v":10,"d":"","po":326},"50167":{"n":"Dragey-Ronthon","p":10539,"e":4.5,"v":14,"d":"","po":789},"50168":{"n":"Ducey-Les Chéris","p":13228,"e":0.8,"v":17,"d":"","po":2829},"50169":{"n":"Écausseville","p":10781,"e":7.8,"v":7,"d":"","po":112},"50172":{"n":"Émondeville","p":12745,"e":0.1,"v":10,"d":"","po":342},"50174":{"n":"Équilly","p":10876,"e":0.6,"v":8,"d":"","po":194},"50175":{"n":"Éroudeville","p":9533,"e":0.9,"v":10,"d":"","po":180},"50176":{"n":"L'Étang-Bertrand","p":11738,"e":7.1,"v":15,"d":"","po":344},"50177":{"n":"Étienville","p":8943,"e":1.4,"v":9,"d":"","po":376},"50178":{"n":"Fermanville","p":9624,"e":3.7,"v":9,"d":"","po":1291},"50181":{"n":"Feugères","p":9486,"e":5.9,"v":12,"d":"","po":353},"50182":{"n":"La Feuillie","p":10752,"e":2.9,"v":19,"d":"","po":299},"50183":{"n":"Fierville-les-Mines","p":11406,"e":7.3,"v":5,"d":"","po":349},"50184":{"n":"Flamanville","p":11777,"e":3.1,"v":16,"d":"","po":1682},"50185":{"n":"Fleury","p":11909,"e":3.1,"v":11,"d":"","po":1085},"50186":{"n":"Flottemanville","p":11435,"e":5.5,"v":7,"d":"","po":227},"50188":{"n":"Folligny","p":11998,"e":4.3,"v":16,"d":"","po":1109},"50190":{"n":"Fontenay-sur-Mer","p":11734,"e":6.0,"v":6,"d":"","po":164},"50192":{"n":"Fourneaux","p":9789,"e":4.1,"v":18,"d":"","po":131},"50193":{"n":"Le Fresne-Poret","p":11771,"e":1.0,"v":14,"d":"","po":222},"50194":{"n":"Fresville","p":11270,"e":5.0,"v":12,"d":"","po":377},"50195":{"n":"Gathemo","p":10802,"e":-0.2,"v":19,"d":"","po":268},"50196":{"n":"Gatteville-le-Phare","p":13042,"e":5.0,"v":8,"d":"","po":468},"50197":{"n":"Gavray-sur-Sienne","p":12616,"e":2.2,"v":16,"d":"","po":2028},"50198":{"n":"Geffosses","p":8887,"e":7.1,"v":8,"d":"","po":498},"50199":{"n":"Genêts","p":12617,"e":1.2,"v":5,"d":"","po":453},"50200":{"n":"Ger","p":11532,"e":1.4,"v":12,"d":"","po":818},"50205":{"n":"La Godefroy","p":12581,"e":3.7,"v":13,"d":"","po":295},"50207":{"n":"Golleville","p":11029,"e":6.3,"v":6,"d":"","po":165},"50208":{"n":"Gonfreville","p":10783,"e":6.0,"v":5,"d":"","po":162},"50209":{"n":"Gonneville-Le Theil","p":10543,"e":-1.1,"v":14,"d":"","po":1504},"50210":{"n":"Gorges","p":12088,"e":-1.8,"v":16,"d":"","po":347},"50214":{"n":"Gouvets","p":9053,"e":4.0,"v":6,"d":"","po":291},"50215":{"n":"Gouville-sur-Mer","p":9152,"e":7.5,"v":17,"d":"","po":3266},"50216":{"n":"Graignes-Mesnil-Angot","p":11620,"e":1.6,"v":18,"d":"","po":800},"50217":{"n":"Le Grand-Celland","p":9681,"e":3.4,"v":8,"d":"","po":595},"50218":{"n":"Granville","p":11501,"e":1.2,"v":126,"d":"","po":12799},"50219":{"n":"Gratot","p":8845,"e":4.5,"v":12,"d":"","po":674},"50221":{"n":"Grimesnil","p":10280,"e":0.9,"v":13,"d":"","po":70},"50222":{"n":"Grosville","p":12253,"e":3.8,"v":13,"d":"","po":804},"50225":{"n":"Le Guislain","p":10401,"e":7.1,"v":6,"d":"","po":139},"50227":{"n":"Le Ham","p":11391,"e":-1.6,"v":20,"d":"","po":312},"50228":{"n":"Hambye","p":10335,"e":-1.9,"v":12,"d":"","po":1077},"50229":{"n":"Hamelin","p":12387,"e":3.4,"v":17,"d":"","po":109},"50230":{"n":"Hardinvast","p":8974,"e":5.7,"v":18,"d":"","po":924},"50231":{"n":"Hauteville-sur-Mer","p":10227,"e":7.6,"v":8,"d":"","po":707},"50232":{"n":"Hauteville-la-Guichard","p":10793,"e":6.2,"v":7,"d":"","po":452},"50233":{"n":"Hautteville-Bocage","p":10439,"e":-1.0,"v":5,"d":"","po":154},"50234":{"n":"La Haye-Bellefond","p":10255,"e":7.4,"v":8,"d":"","po":67},"50235":{"n":"La Haye-d'Ectot","p":12998,"e":3.6,"v":19,"d":"","po":285},"50236":{"n":"La Haye","p":10809,"e":2.3,"v":16,"d":"","po":3986},"50237":{"n":"La Haye-Pesnel","p":12992,"e":2.0,"v":8,"d":"","po":1261},"50238":{"n":"Héauville","p":11375,"e":6.7,"v":6,"d":"","po":462},"50239":{"n":"Thèreval","p":11220,"e":-1.7,"v":9,"d":"","po":1781},"50240":{"n":"Helleville","p":10683,"e":7.2,"v":5,"d":"","po":563},"50241":{"n":"Hémevez","p":11434,"e":5.2,"v":12,"d":"","po":186},"50243":{"n":"Heugueville-sur-Sienne","p":8789,"e":7.1,"v":8,"d":"","po":462},"50246":{"n":"Hiesville","p":9527,"e":-1.5,"v":14,"d":"","po":72},"50247":{"n":"Hocquigny","p":11416,"e":4.7,"v":20,"d":"","po":194},"50251":{"n":"Huberville","p":12631,"e":1.0,"v":7,"d":"","po":361},"50252":{"n":"Hudimesnil","p":10958,"e":5.8,"v":10,"d":"","po":926},"50253":{"n":"Huisnes-sur-Mer","p":11161,"e":2.8,"v":13,"d":"","po":168},"50256":{"n":"Isigny-le-Buat","p":10788,"e":0.3,"v":17,"d":"","po":3187},"50258":{"n":"Joganville","p":11818,"e":-0.5,"v":15,"d":"","po":85},"50259":{"n":"Juilley","p":9249,"e":1.2,"v":10,"d":"","po":664},"50260":{"n":"Juvigny les Vallées","p":10277,"e":3.6,"v":11,"d":"","po":1678},"50261":{"n":"Lamberville","p":10261,"e":4.4,"v":15,"d":"","po":167},"50262":{"n":"La Lande-d'Airou","p":11353,"e":5.7,"v":9,"d":"","po":535},"50263":{"n":"Lapenty","p":12283,"e":6.0,"v":7,"d":"","po":382},"50265":{"n":"Laulne","p":11018,"e":6.3,"v":7,"d":"","po":185},"50266":{"n":"Lengronne","p":10752,"e":2.5,"v":19,"d":"","po":463},"50267":{"n":"Lessay","p":11757,"e":7.1,"v":7,"d":"","po":2255},"50268":{"n":"Lestre","p":12025,"e":2.9,"v":9,"d":"","po":244},"50269":{"n":"Liesville-sur-Douve","p":9725,"e":6.2,"v":13,"d":"","po":214},"50270":{"n":"Lieusaint","p":11648,"e":-1.9,"v":5,"d":"","po":400},"50271":{"n":"Lingeard","p":9603,"e":-0.7,"v":10,"d":"","po":88},"50272":{"n":"Tourneville-sur-Mer","p":11274,"e":2.8,"v":6,"d":"","po":1668},"50273":{"n":"Montsenelle","p":11666,"e":0.2,"v":20,"d":"","po":1438},"50274":{"n":"Les Loges-Marchis","p":10979,"e":-2.0,"v":16,"d":"","po":1028},"50275":{"n":"Les Loges-sur-Brécey","p":12412,"e":3.7,"v":6,"d":"","po":117},"50276":{"n":"Lolif","p":11411,"e":2.0,"v":14,"d":"","po":608},"50277":{"n":"Longueville","p":9891,"e":-0.9,"v":10,"d":"","po":612},"50278":{"n":"Le Loreur","p":12507,"e":4.6,"v":5,"d":"","po":262},"50279":{"n":"Le Lorey","p":10775,"e":-0.4,"v":6,"d":"","po":570},"50281":{"n":"La Lucerne-d'Outremer","p":10135,"e":6.2,"v":9,"d":"","po":847},"50282":{"n":"Le Luot","p":10787,"e":4.3,"v":11,"d":"","po":285},"50283":{"n":"La Luzerne","p":11301,"e":0.2,"v":18,"d":"","po":81},"50285":{"n":"Magneville","p":12268,"e":-1.9,"v":11,"d":"","po":311},"50288":{"n":"Marcey-les-Grèves","p":10193,"e":0.8,"v":6,"d":"","po":1286},"50289":{"n":"Marchésieux","p":11283,"e":-0.2,"v":11,"d":"","po":684},"50290":{"n":"Marcilly","p":9454,"e":5.4,"v":19,"d":"","po":353},"50291":{"n":"Margueray","p":9368,"e":-1.2,"v":16,"d":"","po":117},"50292":{"n":"Marigny-Le-Lozon","p":9696,"e":4.5,"v":14,"d":"","po":2754},"50294":{"n":"Martinvast","p":12412,"e":4.2,"v":8,"d":"","po":1340},"50295":{"n":"Maupertuis","p":10478,"e":3.7,"v":12,"d":"","po":147},"50296":{"n":"Maupertus-sur-Mer","p":8851,"e":5.8,"v":6,"d":"","po":229},"50297":{"n":"La Meauffe","p":11333,"e":1.0,"v":20,"d":"","po":998},"50298":{"n":"Méautis","p":13218,"e":-1.9,"v":5,"d":"","po":648},"50299":{"n":"Le Mesnil","p":10348,"e":3.4,"v":10,"d":"","po":204},"50300":{"n":"Le Mesnil-Adelée","p":9947,"e":3.5,"v":20,"d":"","po":158},"50302":{"n":"Le Mesnil-Amey","p":10613,"e":6.3,"v":19,"d":"","po":287},"50304":{"n":"Le Mesnil-Aubert","p":12230,"e":1.9,"v":6,"d":"","po":195},"50305":{"n":"Le Mesnil-au-Val","p":10794,"e":-0.5,"v":13,"d":"","po":727},"50310":{"n":"Le Mesnil-Eury","p":12557,"e":1.0,"v":12,"d":"","po":180},"50311":{"n":"Le Mesnil-Garnier","p":11476,"e":-0.7,"v":6,"d":"","po":222},"50312":{"n":"Le Mesnil-Gilbert","p":11913,"e":2.4,"v":10,"d":"","po":142},"50315":{"n":"Le Mesnillard","p":12840,"e":2.3,"v":6,"d":"","po":251},"50317":{"n":"Le Mesnil-Ozenne","p":12443,"e":7.4,"v":15,"d":"","po":269},"50321":{"n":"Le Mesnil-Rouxelin","p":10430,"e":3.1,"v":13,"d":"","po":470},"50324":{"n":"Le Mesnil-Véneron","p":10127,"e":-0.2,"v":16,"d":"","po":108},"50326":{"n":"Le Mesnil-Villeman","p":9647,"e":5.1,"v":11,"d":"","po":237},"50327":{"n":"La Meurdraquière","p":10306,"e":3.9,"v":7,"d":"","po":195},"50328":{"n":"Millières","p":9756,"e":7.3,"v":18,"d":"","po":760},"50332":{"n":"Les Moitiers-d'Allonne","p":10018,"e":5.4,"v":10,"d":"","po":730},"50334":{"n":"Montabot","p":11700,"e":5.4,"v":9,"d":"","po":272},"50335":{"n":"Montaigu-la-Brisette","p":10905,"e":6.0,"v":5,"d":"","po":499},"50336":{"n":"Montaigu-les-Bois","p":12439,"e":5.7,"v":16,"d":"","po":208},"50338":{"n":"Montbray","p":12344,"e":-0.0,"v":13,"d":"","po":325},"50340":{"n":"Montcuit","p":9273,"e":5.3,"v":19,"d":"","po":185},"50341":{"n":"Montebourg","p":11152,"e":7.9,"v":19,"d":"","po":1951},"50342":{"n":"Montfarville","p":10164,"e":0.6,"v":5,"d":"","po":798},"50345":{"n":"Monthuchon","p":13057,"e":6.6,"v":12,"d":"","po":702},"50347":{"n":"Montjoie-Saint-Martin","p":12067,"e":2.2,"v":17,"d":"","po":250},"50349":{"n":"Montmartin-sur-Mer","p":8759,"e":4.6,"v":17,"d":"","po":1413},"50350":{"n":"Montpinchon","p":11475,"e":0.0,"v":5,"d":"","po":543},"50351":{"n":"Montrabot","p":9794,"e":5.5,"v":11,"d":"","po":79},"50352":{"n":"Montreuil-sur-Lozon","p":10873,"e":1.6,"v":6,"d":"","po":345},"50353":{"n":"Le Mont-Saint-Michel","p":12138,"e":2.7,"v":18,"d":"","po":23},"50356":{"n":"Moon-sur-Elle","p":10746,"e":4.3,"v":10,"d":"","po":779},"50357":{"n":"Morigny","p":11855,"e":2.9,"v":15,"d":"","po":70},"50359":{"n":"Mortain-Bocage","p":11682,"e":5.9,"v":11,"d":"","po":2954},"50360":{"n":"Morville","p":12908,"e":-0.6,"v":14,"d":"","po":278},"50361":{"n":"La Mouche","p":10949,"e":-0.8,"v":9,"d":"","po":246},"50362":{"n":"Moulines","p":11364,"e":4.3,"v":5,"d":"","po":281},"50363":{"n":"Moyon Villages","p":12421,"e":6.2,"v":9,"d":"","po":1465},"50364":{"n":"Muneville-le-Bingard","p":12275,"e":3.7,"v":7,"d":"","po":730},"50365":{"n":"Muneville-sur-Mer","p":10794,"e":5.9,"v":16,"d":"","po":494},"50368":{"n":"Nay","p":10515,"e":-1.9,"v":20,"d":"","po":68},"50369":{"n":"Négreville","p":11035,"e":6.0,"v":14,"d":"","po":844},"50370":{"n":"Néhou","p":10123,"e":5.9,"v":12,"d":"","po":608},"50371":{"n":"Le Neufbourg","p":10224,"e":-1.1,"v":6,"d":"","po":399},"50372":{"n":"Neufmesnil","p":11822,"e":5.1,"v":5,"d":"","po":174},"50373":{"n":"Neuville-au-Plain","p":11947,"e":8.0,"v":15,"d":"","po":84},"50374":{"n":"Neuville-en-Beaumont","p":9341,"e":5.1,"v":20,"d":"","po":25},"50376":{"n":"Nicorps","p":11466,"e":2.7,"v":17,"d":"","po":361},"50378":{"n":"Notre-Dame-de-Cenilly","p":10491,"e":3.6,"v":18,"d":"","po":631},"50379":{"n":"Notre-Dame-de-Livoye","p":12769,"e":4.2,"v":16,"d":"","po":166},"50382":{"n":"Nouainville","p":10353,"e":0.8,"v":7,"d":"","po":620},"50384":{"n":"Octeville-l'Avenel","p":10611,"e":0.4,"v":9,"d":"","po":233},"50387":{"n":"Orglandes","p":9238,"e":6.1,"v":6,"d":"","po":349},"50388":{"n":"Orval sur Sienne","p":11948,"e":4.0,"v":5,"d":"","po":1222},"50389":{"n":"Ouville","p":11416,"e":6.1,"v":8,"d":"","po":447},"50390":{"n":"Ozeville","p":9591,"e":3.4,"v":7,"d":"","po":156},"50391":{"n":"Grandparigny","p":10305,"e":7.0,"v":7,"d":"","po":2623},"50393":{"n":"Percy-en-Normandie","p":11277,"e":4.2,"v":7,"d":"","po":2628},"50394":{"n":"Périers","p":9696,"e":7.7,"v":17,"d":"","po":2355},"50395":{"n":"La Pernelle","p":12346,"e":4.9,"v":5,"d":"","po":287},"50397":{"n":"Perriers-en-Beauficel","p":10995,"e":3.6,"v":16,"d":"","po":207},"50398":{"n":"Le Perron","p":12912,"e":1.1,"v":12,"d":"","po":193},"50399":{"n":"Le Petit-Celland","p":10308,"e":4.6,"v":9,"d":"","po":175},"50400":{"n":"Picauville","p":10493,"e":0.4,"v":7,"d":"","po":3222},"50401":{"n":"Pierreville","p":10237,"e":-1.9,"v":15,"d":"","po":759},"50402":{"n":"Les Pieux","p":11888,"e":-1.0,"v":14,"d":"","po":3266},"50403":{"n":"Pirou","p":12025,"e":4.9,"v":11,"d":"","po":1486},"50405":{"n":"Le Plessis-Lastelle","p":10232,"e":3.6,"v":7,"d":"","po":238},"50407":{"n":"Poilley","p":9724,"e":-0.4,"v":7,"d":"","po":968},"50408":{"n":"Pontaubault","p":13254,"e":3.9,"v":16,"d":"","po":576},"50409":{"n":"Pont-Hébert","p":11915,"e":1.8,"v":16,"d":"","po":1902},"50410":{"n":"Pontorson","p":10311,"e":-1.6,"v":12,"d":"","po":4319},"50411":{"n":"Ponts","p":9209,"e":3.0,"v":11,"d":"","po":684},"50412":{"n":"Port-Bail-sur-Mer","p":11796,"e":1.3,"v":20,"d":"","po":2522},"50413":{"n":"Précey","p":10224,"e":-1.1,"v":17,"d":"","po":567},"50417":{"n":"Quettehou","p":8844,"e":0.3,"v":14,"d":"","po":1798},"50419":{"n":"Quettreville-sur-Sienne","p":12713,"e":3.0,"v":17,"d":"","po":3181},"50420":{"n":"Quibou","p":8841,"e":-0.3,"v":10,"d":"","po":842},"50421":{"n":"Quinéville","p":11085,"e":4.2,"v":18,"d":"","po":260},"50422":{"n":"Raids","p":11331,"e":-1.5,"v":18,"d":"","po":208},"50423":{"n":"Rampan","p":11062,"e":1.2,"v":5,"d":"","po":227},"50425":{"n":"Rauville-la-Bigot","p":10382,"e":2.4,"v":5,"d":"","po":1091},"50426":{"n":"Rauville-la-Place","p":12152,"e":4.8,"v":13,"d":"","po":388},"50428":{"n":"Reffuveille","p":9260,"e":2.1,"v":20,"d":"","po":537},"50429":{"n":"Regnéville-sur-Mer","p":10520,"e":3.8,"v":16,"d":"","po":731},"50430":{"n":"Reigneville-Bocage","p":11324,"e":6.0,"v":13,"d":"","po":38},"50431":{"n":"Remilly Les Marais","p":10730,"e":-0.4,"v":20,"d":"","po":1064},"50433":{"n":"Réville","p":11188,"e":6.9,"v":9,"d":"","po":1038},"50435":{"n":"Rocheville","p":10917,"e":-0.4,"v":11,"d":"","po":608},"50436":{"n":"Romagny Fontenay","p":10072,"e":5.7,"v":9,"d":"","po":1247},"50437":{"n":"Roncey","p":10004,"e":8.0,"v":9,"d":"","po":776},"50442":{"n":"Le Rozel","p":9508,"e":-0.2,"v":6,"d":"","po":244},"50443":{"n":"Sacey","p":11636,"e":-1.4,"v":14,"d":"","po":512},"50444":{"n":"Saint-Amand-Villages","p":9949,"e":7.9,"v":20,"d":"","po":2523},"50445":{"n":"Saint-André-de-Bohon","p":9367,"e":1.1,"v":19,"d":"","po":369},"50446":{"n":"Saint-André-de-l'Épine","p":11645,"e":-0.7,"v":9,"d":"","po":553},"50447":{"n":"Saint-Aubin-des-Préaux","p":10981,"e":6.2,"v":20,"d":"","po":475},"50448":{"n":"Saint-Aubin-de-Terregatte","p":9897,"e":6.0,"v":9,"d":"","po":651},"50450":{"n":"Saint-Barthélemy","p":12278,"e":3.8,"v":11,"d":"","po":338},"50451":{"n":"Saint-Brice","p":11789,"e":0.6,"v":5,"d":"","po":136},"50452":{"n":"Saint-Brice-de-Landelles","p":10570,"e":0.4,"v":19,"d":"","po":651},"50453":{"n":"Sainte-Cécile","p":9213,"e":3.3,"v":5,"d":"","po":785},"50454":{"n":"Saint-Christophe-du-Foc","p":11278,"e":4.2,"v":20,"d":"","po":412},"50455":{"n":"Saint-Clair-sur-l'Elle","p":10512,"e":6.6,"v":6,"d":"","po":973},"50456":{"n":"Saint-Clément-Rancoudray","p":9449,"e":3.5,"v":14,"d":"","po":548},"50457":{"n":"Sainte-Colombe","p":10994,"e":0.6,"v":15,"d":"","po":181},"50461":{"n":"Saint-Cyr","p":9037,"e":-1.7,"v":15,"d":"","po":211},"50462":{"n":"Saint-Cyr-du-Bailleul","p":9009,"e":0.8,"v":12,"d":"","po":349},"50463":{"n":"Saint-Denis-le-Gast","p":11637,"e":4.5,"v":8,"d":"","po":527},"50464":{"n":"Saint-Denis-le-Vêtu","p":9153,"e":1.9,"v":19,"d":"","po":605},"50467":{"n":"Saint-Floxel","p":12953,"e":6.4,"v":11,"d":"","po":490},"50468":{"n":"Saint-Fromond","p":9866,"e":-1.4,"v":7,"d":"","po":749},"50469":{"n":"Sainte-Geneviève","p":10342,"e":6.3,"v":18,"d":"","po":309},"50471":{"n":"Saint-Georges-de-la-Rivière","p":8963,"e":-1.7,"v":11,"d":"","po":253},"50472":{"n":"Saint-Georges-de-Livoye","p":10829,"e":3.4,"v":17,"d":"","po":205},"50473":{"n":"Saint-Georges-d'Elle","p":10414,"e":-0.7,"v":9,"d":"","po":378},"50474":{"n":"Saint-Georges-de-Rouelley","p":12040,"e":4.4,"v":17,"d":"","po":529},"50475":{"n":"Saint-Georges-Montcocq","p":11068,"e":4.2,"v":12,"d":"","po":983},"50476":{"n":"Saint-Germain-d'Elle","p":12163,"e":-0.4,"v":9,"d":"","po":209},"50478":{"n":"Saint-Germain-de-Tournebut","p":13087,"e":5.6,"v":18,"d":"","po":418},"50479":{"n":"Saint-Germain-de-Varreville","p":9402,"e":6.3,"v":17,"d":"","po":109},"50480":{"n":"Saint-Germain-le-Gaillard","p":10803,"e":5.0,"v":17,"d":"","po":795},"50481":{"n":"Saint-Germain-sur-Ay","p":9124,"e":2.1,"v":5,"d":"","po":920},"50482":{"n":"Saint-Germain-sur-Sèves","p":11259,"e":0.4,"v":13,"d":"","po":174},"50483":{"n":"Saint-Gilles","p":12004,"e":-1.3,"v":16,"d":"","po":987},"50484":{"n":"Saint-Hilaire-du-Harcouët","p":9541,"e":5.7,"v":48,"d":"","po":5735},"50486":{"n":"Saint-Jacques-de-Néhou","p":11571,"e":6.4,"v":14,"d":"","po":629},"50487":{"n":"Saint-James","p":10726,"e":4.6,"v":20,"d":"","po":4966},"50488":{"n":"Saint-Jean-de-Daye","p":8827,"e":-1.4,"v":9,"d":"","po":645},"50489":{"n":"Saint-Jean-de-la-Haize","p":10744,"e":0.7,"v":19,"d":"","po":538},"50490":{"n":"Saint-Jean-de-la-Rivière","p":12417,"e":3.3,"v":15,"d":"","po":366},"50491":{"n":"Saint-Jean-de-Savigny","p":12314,"e":0.6,"v":14,"d":"","po":422},"50492":{"n":"Saint-Jean-d'Elle","p":11586,"e":1.0,"v":17,"d":"","po":2535},"50493":{"n":"Saint-Jean-des-Champs","p":9726,"e":2.6,"v":12,"d":"","po":1521},"50495":{"n":"Saint-Jean-du-Corail-des-Bois","p":10615,"e":4.9,"v":13,"d":"","po":75},"50496":{"n":"Saint-Jean-le-Thomas","p":10964,"e":3.5,"v":7,"d":"","po":395},"50498":{"n":"Saint-Joseph","p":9023,"e":-1.3,"v":20,"d":"","po":817},"50499":{"n":"Saint-Laurent-de-Cuves","p":10864,"e":6.0,"v":13,"d":"","po":499},"50500":{"n":"Saint-Laurent-de-Terregatte","p":10445,"e":0.3,"v":17,"d":"","po":645},"50502":{"n":"Saint-Lô","p":10422,"e":5.4,"v":149,"d":"","po":19352},"50504":{"n":"Saint-Louet-sur-Vire","p":11769,"e":7.2,"v":8,"d":"","po":209},"50505":{"n":"Saint-Loup","p":10591,"e":-0.9,"v":18,"d":"","po":678},"50506":{"n":"Saint-Malo-de-la-Lande","p":10771,"e":2.9,"v":8,"d":"","po":462},"50507":{"n":"Saint-Marcouf","p":10189,"e":7.8,"v":15,"d":"","po":353},"50509":{"n":"Sainte-Marie-du-Mont","p":10827,"e":3.9,"v":18,"d":"","po":694},"50510":{"n":"Saint-Martin-d'Aubigny","p":10341,"e":6.6,"v":14,"d":"","po":606},"50511":{"n":"Saint-Martin-d'Audouville","p":9518,"e":6.3,"v":19,"d":"","po":153},"50512":{"n":"Saint-Martin-de-Bonfossé","p":11493,"e":5.2,"v":16,"d":"","po":536},"50513":{"n":"Saint-Martin-de-Cenilly","p":11502,"e":2.9,"v":14,"d":"","po":206},"50514":{"n":"Chaulieu","p":13209,"e":0.9,"v":10,"d":"","po":287},"50517":{"n":"Saint-Martin-de-Varreville","p":10620,"e":-0.3,"v":19,"d":"","po":170},"50518":{"n":"Saint-Martin-le-Bouillant","p":12220,"e":3.6,"v":13,"d":"","po":312},"50519":{"n":"Saint-Martin-le-Gréard","p":13125,"e":7.0,"v":15,"d":"","po":618},"50521":{"n":"Saint-Maur-des-Bois","p":11392,"e":5.9,"v":16,"d":"","po":157},"50522":{"n":"Saint-Maurice-en-Cotentin","p":11971,"e":0.6,"v":18,"d":"","po":248},"50523":{"n":"Sainte-Mère-Église","p":11371,"e":1.6,"v":5,"d":"","po":2910},"50525":{"n":"Saint-Michel-de-Montjoie","p":10238,"e":6.2,"v":5,"d":"","po":344},"50528":{"n":"Saint-Nicolas-de-Pierrepont","p":9355,"e":-1.1,"v":15,"d":"","po":299},"50529":{"n":"Saint-Nicolas-des-Bois","p":12466,"e":4.4,"v":13,"d":"","po":92},"50531":{"n":"Saint-Ovin","p":11289,"e":5.7,"v":7,"d":"","po":763},"50532":{"n":"Saint-Pair-sur-Mer","p":11708,"e":0.5,"v":15,"d":"","po":4372},"50533":{"n":"Saint-Patrice-de-Claids","p":13308,"e":5.8,"v":5,"d":"","po":177},"50535":{"n":"Le Parc","p":11675,"e":3.9,"v":18,"d":"","po":907},"50536":{"n":"Saint-Pierre-d'Arthéglise","p":10945,"e":1.0,"v":15,"d":"","po":169},"50537":{"n":"Saint-Pierre-de-Coutances","p":12874,"e":-1.3,"v":15,"d":"","po":396},"50538":{"n":"Saint-Pierre-de-Semilly","p":11124,"e":-0.9,"v":12,"d":"","po":428},"50539":{"n":"Saint-Pierre-Église","p":10190,"e":-1.6,"v":9,"d":"","po":1797},"50540":{"n":"Saint-Pierre-Langers","p":10414,"e":0.9,"v":18,"d":"","po":621},"50541":{"n":"Saint-Planchers","p":12635,"e":7.4,"v":12,"d":"","po":1451},"50542":{"n":"Saint-Pois","p":10071,"e":6.1,"v":10,"d":"","po":462},"50543":{"n":"Saint-Quentin-sur-le-Homme","p":10594,"e":7.2,"v":10,"d":"","po":1340},"50546":{"n":"Bourgvallées","p":12180,"e":7.8,"v":13,"d":"","po":3319},"50548":{"n":"Saint-Sauveur-de-Pierrepont","p":11953,"e":-0.3,"v":12,"d":"","po":122},"50549":{"n":"Saint-Sauveur-la-Pommeraye","p":12494,"e":5.1,"v":14,"d":"","po":401},"50550":{"n":"Saint-Sauveur-Villages","p":10497,"e":7.8,"v":5,"d":"","po":3250},"50551":{"n":"Saint-Sauveur-le-Vicomte","p":10352,"e":0.1,"v":19,"d":"","po":2088},"50552":{"n":"Saint-Sébastien-de-Raids","p":10147,"e":1.1,"v":7,"d":"","po":325},"50553":{"n":"Saint-Senier-de-Beuvron","p":11321,"e":0.8,"v":9,"d":"","po":329},"50554":{"n":"Saint-Senier-sous-Avranches","p":9956,"e":4.7,"v":10,"d":"","po":1426},"50556":{"n":"Sainte-Suzanne-sur-Vire","p":11586,"e":3.9,"v":15,"d":"","po":694},"50562":{"n":"Saint-Vaast-la-Hougue","p":12601,"e":0.9,"v":13,"d":"","po":1666},"50563":{"n":"Saint-Vigor-des-Monts","p":12749,"e":6.4,"v":17,"d":"","po":283},"50564":{"n":"Terre-et-Marais","p":10416,"e":2.7,"v":19,"d":"","po":1288},"50565":{"n":"Sartilly-Baie-Bocage","p":11214,"e":5.0,"v":8,"d":"","po":2843},"50567":{"n":"Saussemesnil","p":10810,"e":1.0,"v":19,"d":"","po":912},"50568":{"n":"Saussey","p":10355,"e":5.6,"v":14,"d":"","po":458},"50569":{"n":"Savigny","p":10365,"e":-1.2,"v":19,"d":"","po":433},"50570":{"n":"Savigny-le-Vieux","p":11850,"e":2.6,"v":18,"d":"","po":402},"50571":{"n":"Sébeville","p":9040,"e":-0.7,"v":16,"d":"","po":34},"50572":{"n":"Sénoville","p":11154,"e":5.0,"v":9,"d":"","po":191},"50574":{"n":"Servon","p":11202,"e":4.5,"v":19,"d":"","po":257},"50575":{"n":"Sideville","p":9906,"e":-1.8,"v":11,"d":"","po":840},"50576":{"n":"Siouville-Hague","p":10251,"e":6.2,"v":18,"d":"","po":936},"50577":{"n":"Sortosville-en-Beaumont","p":10900,"e":-0.9,"v":8,"d":"","po":302},"50578":{"n":"Sortosville","p":11400,"e":-0.9,"v":5,"d":"","po":78},"50579":{"n":"Sottevast","p":10334,"e":1.5,"v":11,"d":"","po":1455},"50580":{"n":"Sotteville","p":10049,"e":2.3,"v":20,"d":"","po":483},"50582":{"n":"Sourdeval","p":11361,"e":-0.2,"v":18,"d":"","po":3040},"50584":{"n":"Subligny","p":12242,"e":7.3,"v":10,"d":"","po":377},"50585":{"n":"Surtainville","p":11194,"e":6.7,"v":9,"d":"","po":1169},"50587":{"n":"Taillepied","p":10522,"e":-0.0,"v":7,"d":"","po":17},"50588":{"n":"Tamerville","p":11719,"e":4.4,"v":20,"d":"","po":693},"50589":{"n":"Tanis","p":10453,"e":7.7,"v":18,"d":"","po":273},"50590":{"n":"Le Tanu","p":9828,"e":3.8,"v":19,"d":"","po":421},"50591":{"n":"Le Teilleul","p":10158,"e":4.4,"v":5,"d":"","po":1692},"50592":{"n":"Tessy-Bocage","p":9446,"e":-0.7,"v":7,"d":"","po":2219},"50593":{"n":"Teurthéville-Bocage","p":11798,"e":1.5,"v":17,"d":"","po":594},"50594":{"n":"Teurthéville-Hague","p":12293,"e":-1.8,"v":8,"d":"","po":1029},"50596":{"n":"Théville","p":11635,"e":1.7,"v":10,"d":"","po":311},"50597":{"n":"Tirepied-sur-Sée","p":10695,"e":7.5,"v":8,"d":"","po":953},"50598":{"n":"Tocqueville","p":11151,"e":-1.0,"v":9,"d":"","po":257},"50599":{"n":"Tollevast","p":10883,"e":6.7,"v":7,"d":"","po":1650},"50601":{"n":"Torigny-les-Villes","p":12131,"e":5.4,"v":16,"d":"","po":4441},"50603":{"n":"Tourville-sur-Sienne","p":10466,"e":7.5,"v":7,"d":"","po":772},"50604":{"n":"Tréauville","p":11348,"e":6.2,"v":17,"d":"","po":727},"50606":{"n":"Tribehou","p":12329,"e":-1.9,"v":9,"d":"","po":511},"50607":{"n":"La Trinité","p":10706,"e":4.9,"v":5,"d":"","po":401},"50609":{"n":"Turqueville","p":9258,"e":7.0,"v":14,"d":"","po":127},"50610":{"n":"Urville","p":12944,"e":3.1,"v":9,"d":"","po":196},"50612":{"n":"Vains","p":10098,"e":7.2,"v":11,"d":"","po":760},"50613":{"n":"Valcanville","p":9738,"e":3.7,"v":5,"d":"","po":391},"50615":{"n":"Valognes","p":9595,"e":2.7,"v":48,"d":"","po":6896},"50616":{"n":"Le Val-Saint-Père","p":11527,"e":-0.5,"v":10,"d":"","po":1914},"50617":{"n":"Varenguebec","p":13299,"e":4.3,"v":18,"d":"","po":329},"50618":{"n":"Varouville","p":11580,"e":2.6,"v":16,"d":"","po":222},"50619":{"n":"Le Vast","p":9749,"e":-1.5,"v":12,"d":"","po":325},"50621":{"n":"Vaudreville","p":9674,"e":-0.3,"v":15,"d":"","po":72},"50624":{"n":"La Vendelée","p":9914,"e":3.8,"v":10,"d":"","po":468},"50626":{"n":"Ver","p":10602,"e":-0.0,"v":6,"d":"","po":384},"50628":{"n":"Vernix","p":11233,"e":7.4,"v":12,"d":"","po":155},"50629":{"n":"Vesly","p":13146,"e":6.2,"v":17,"d":"","po":732},"50633":{"n":"Le Vicel","p":9879,"e":1.5,"v":6,"d":"","po":119},"50634":{"n":"Videcosville","p":10367,"e":0.8,"v":11,"d":"","po":88},"50637":{"n":"Villebaudon","p":10224,"e":6.6,"v":19,"d":"","po":325},"50639":{"n":"Villedieu-les-Poêles-Rouffigny","p":10147,"e":3.2,"v":6,"d":"","po":3845},"50641":{"n":"Villiers-Fossard","p":12904,"e":1.4,"v":11,"d":"","po":644},"50643":{"n":"Virandeville","p":9430,"e":6.0,"v":15,"d":"","po":771},"50647":{"n":"Yquelon","p":12703,"e":1.5,"v":16,"d":"","po":1186},"50648":{"n":"Yvetot-Bocage","p":11289,"e":-1.0,"v":6,"d":"","po":1188}}